coordencode/__init__.py
coordencode/int_to_xcoords.py
coordencode/ith_middle.py
coordencode/neuralfloat.py
coordencode/xcoords_to_int.py
coordencode-0.0.1.dist-info/LICENSE.md
coordencode-0.0.1.dist-info/WHEEL
coordencode-0.0.1.dist-info/METADATA
coordencode-0.0.1.dist-info/RECORD
